{
  "id": "88d21775-2d0e-4442-bbda-6dda167d049f",
  "prevId": "d4557b0c-d463-43c8-9b2a-e24d91a5171c",
  "version": "7",
  "dialect": "postgresql",
  "tables": {
    "public.paciente": {
      "name": "paciente",
      "schema": "",
      "columns": {
        "id": {
          "name": "id",
          "type": "text",
          "primaryKey": true,
          "notNull": true
        },
        "nome": {
          "name": "nome",
          "type": "text",
          "primaryKey": false,
          "notNull": true
        },
        "email": {
          "name": "email",
          "type": "text",
          "primaryKey": false,
          "notNull": true
        },
        "telefone": {
          "name": "telefone",
          "type": "text",
          "primaryKey": false,
          "notNull": true
        },
        "cpf": {
          "name": "cpf",
          "type": "text",
          "primaryKey": false,
          "notNull": true
        },
        "data_nascimento": {
          "name": "data_nascimento",
          "type": "date",
          "primaryKey": false,
          "notNull": true
        },
        "criado_em": {
          "name": "criado_em",
          "type": "timestamp",
          "primaryKey": false,
          "notNull": true,
          "default": "now()"
        },
        "ativo": {
          "name": "ativo",
          "type": "boolean",
          "primaryKey": false,
          "notNull": true,
          "default": true
        }
      },
      "indexes": {},
      "foreignKeys": {},
      "compositePrimaryKeys": {},
      "uniqueConstraints": {
        "paciente_email_unique": {
          "name": "paciente_email_unique",
          "nullsNotDistinct": false,
          "columns": [
            "email"
          ]
        },
        "paciente_cpf_unique": {
          "name": "paciente_cpf_unique",
          "nullsNotDistinct": false,
          "columns": [
            "cpf"
          ]
        }
      },
      "policies": {},
      "checkConstraints": {},
      "isRLSEnabled": false
    },
    "public.cobranca": {
      "name": "cobranca",
      "schema": "",
      "columns": {
        "id": {
          "name": "id",
          "type": "text",
          "primaryKey": true,
          "notNull": true
        },
        "nome": {
          "name": "nome",
          "type": "text",
          "primaryKey": false,
          "notNull": true
        },
        "parcelas_maximas": {
          "name": "parcelas_maximas",
          "type": "integer",
          "primaryKey": false,
          "notNull": true,
          "default": 1
        },
        "prazo_maximo": {
          "name": "prazo_maximo",
          "type": "integer",
          "primaryKey": false,
          "notNull": true,
          "default": 30
        },
        "ativo": {
          "name": "ativo",
          "type": "boolean",
          "primaryKey": false,
          "notNull": true,
          "default": true
        },
        "criado_em": {
          "name": "criado_em",
          "type": "timestamp",
          "primaryKey": false,
          "notNull": true,
          "default": "now()"
        }
      },
      "indexes": {},
      "foreignKeys": {},
      "compositePrimaryKeys": {},
      "uniqueConstraints": {
        "cobranca_nome_unique": {
          "name": "cobranca_nome_unique",
          "nullsNotDistinct": false,
          "columns": [
            "nome"
          ]
        }
      },
      "policies": {},
      "checkConstraints": {},
      "isRLSEnabled": false
    },
    "public.plano_pagamento": {
      "name": "plano_pagamento",
      "schema": "",
      "columns": {
        "id": {
          "name": "id",
          "type": "text",
          "primaryKey": true,
          "notNull": true
        },
        "nome": {
          "name": "nome",
          "type": "text",
          "primaryKey": false,
          "notNull": true
        },
        "parcelas_maximas": {
          "name": "parcelas_maximas",
          "type": "integer",
          "primaryKey": false,
          "notNull": true,
          "default": 1
        },
        "prazo_maximo": {
          "name": "prazo_maximo",
          "type": "integer",
          "primaryKey": false,
          "notNull": true,
          "default": 30
        },
        "payment_type": {
          "name": "payment_type",
          "type": "tipo_pagamento",
          "typeSchema": "public",
          "primaryKey": false,
          "notNull": true
        },
        "ativo": {
          "name": "ativo",
          "type": "boolean",
          "primaryKey": false,
          "notNull": true,
          "default": true
        },
        "criado_em": {
          "name": "criado_em",
          "type": "timestamp",
          "primaryKey": false,
          "notNull": true,
          "default": "now()"
        }
      },
      "indexes": {},
      "foreignKeys": {},
      "compositePrimaryKeys": {},
      "uniqueConstraints": {
        "plano_pagamento_nome_unique": {
          "name": "plano_pagamento_nome_unique",
          "nullsNotDistinct": false,
          "columns": [
            "nome"
          ]
        }
      },
      "policies": {},
      "checkConstraints": {},
      "isRLSEnabled": false
    },
    "public.categoria_procedimento": {
      "name": "categoria_procedimento",
      "schema": "",
      "columns": {
        "id": {
          "name": "id",
          "type": "text",
          "primaryKey": true,
          "notNull": true
        },
        "nome": {
          "name": "nome",
          "type": "text",
          "primaryKey": false,
          "notNull": true
        },
        "criado_em": {
          "name": "criado_em",
          "type": "timestamp",
          "primaryKey": false,
          "notNull": true,
          "default": "now()"
        }
      },
      "indexes": {},
      "foreignKeys": {},
      "compositePrimaryKeys": {},
      "uniqueConstraints": {
        "categoria_procedimento_nome_unique": {
          "name": "categoria_procedimento_nome_unique",
          "nullsNotDistinct": false,
          "columns": [
            "nome"
          ]
        }
      },
      "policies": {},
      "checkConstraints": {},
      "isRLSEnabled": false
    },
    "public.procedimento": {
      "name": "procedimento",
      "schema": "",
      "columns": {
        "id": {
          "name": "id",
          "type": "text",
          "primaryKey": true,
          "notNull": true
        },
        "nome": {
          "name": "nome",
          "type": "text",
          "primaryKey": false,
          "notNull": true
        },
        "descricao": {
          "name": "descricao",
          "type": "text",
          "primaryKey": false,
          "notNull": true
        },
        "categoria_id": {
          "name": "categoria_id",
          "type": "text",
          "primaryKey": false,
          "notNull": true
        },
        "valor": {
          "name": "valor",
          "type": "numeric(10, 2)",
          "primaryKey": false,
          "notNull": true
        },
        "duracao_em_minutos": {
          "name": "duracao_em_minutos",
          "type": "integer",
          "primaryKey": false,
          "notNull": true
        },
        "ativo": {
          "name": "ativo",
          "type": "boolean",
          "primaryKey": false,
          "notNull": true,
          "default": true
        },
        "criado_em": {
          "name": "criado_em",
          "type": "timestamp",
          "primaryKey": false,
          "notNull": true,
          "default": "now()"
        }
      },
      "indexes": {},
      "foreignKeys": {
        "procedimento_categoria_id_categoria_procedimento_id_fk": {
          "name": "procedimento_categoria_id_categoria_procedimento_id_fk",
          "tableFrom": "procedimento",
          "tableTo": "categoria_procedimento",
          "columnsFrom": [
            "categoria_id"
          ],
          "columnsTo": [
            "id"
          ],
          "onDelete": "no action",
          "onUpdate": "no action"
        }
      },
      "compositePrimaryKeys": {},
      "uniqueConstraints": {},
      "policies": {},
      "checkConstraints": {},
      "isRLSEnabled": false
    },
    "public.usuario": {
      "name": "usuario",
      "schema": "",
      "columns": {
        "id": {
          "name": "id",
          "type": "text",
          "primaryKey": true,
          "notNull": true
        },
        "username": {
          "name": "username",
          "type": "text",
          "primaryKey": false,
          "notNull": true
        },
        "nome": {
          "name": "nome",
          "type": "text",
          "primaryKey": false,
          "notNull": true
        },
        "email": {
          "name": "email",
          "type": "text",
          "primaryKey": false,
          "notNull": true
        },
        "senha": {
          "name": "senha",
          "type": "text",
          "primaryKey": false,
          "notNull": true
        },
        "role": {
          "name": "role",
          "type": "papel",
          "typeSchema": "public",
          "primaryKey": false,
          "notNull": true,
          "default": "'basico'"
        },
        "ativo": {
          "name": "ativo",
          "type": "boolean",
          "primaryKey": false,
          "notNull": true,
          "default": true
        },
        "criado_em": {
          "name": "criado_em",
          "type": "timestamp",
          "primaryKey": false,
          "notNull": true,
          "default": "now()"
        }
      },
      "indexes": {},
      "foreignKeys": {},
      "compositePrimaryKeys": {},
      "uniqueConstraints": {
        "usuario_username_unique": {
          "name": "usuario_username_unique",
          "nullsNotDistinct": false,
          "columns": [
            "username"
          ]
        },
        "usuario_email_unique": {
          "name": "usuario_email_unique",
          "nullsNotDistinct": false,
          "columns": [
            "email"
          ]
        }
      },
      "policies": {},
      "checkConstraints": {},
      "isRLSEnabled": false
    }
  },
  "enums": {
    "public.papel": {
      "name": "papel",
      "schema": "public",
      "values": [
        "basico",
        "admin",
        "medico"
      ]
    }
  },
  "schemas": {},
  "sequences": {},
  "roles": {},
  "policies": {},
  "views": {},
  "_meta": {
    "columns": {},
    "schemas": {},
    "tables": {}
  }
}